ATEMStreamingXML.py
ATEMStreamingXML-0.1.4.dist-info/LICENSE
ATEMStreamingXML-0.1.4.dist-info/METADATA
ATEMStreamingXML-0.1.4.dist-info/WHEEL
ATEMStreamingXML-0.1.4.dist-info/entry_points.txt
ATEMStreamingXML-0.1.4.dist-info/top_level.txt
ATEMStreamingXML-0.1.4.dist-info/RECORD
