Metadata-Version: 2.1
Name: ATEMStreamingXML
Version: 0.1.4
Summary: Utility to update ATEM Mini Pro Streaming.xml file with new streaming providers.
Home-page: https://github.com/cchurch/ATEMStreamingXML
Author: Nine More Minutes, Inc.
Author-email: chris@ninemoreminutes.com
License: BSD
Project-URL: Documentation, https://github.com/cchurch/ATEMStreamingXML
Project-URL: Source, https://github.com/cchurch/ATEMStreamingXML
Project-URL: Tracker, https://github.com/cchurch/ATEMStreamingXML
Keywords: atem,blackmagic,streaming,rtmp
Platform: UNKNOWN
Classifier: Development Status :: 3 - Alpha
Classifier: Environment :: Console
Classifier: Intended Audience :: End Users/Desktop
Classifier: License :: OSI Approved :: BSD License
Classifier: Operating System :: MacOS :: MacOS X
Classifier: Operating System :: Microsoft :: Windows
Classifier: Programming Language :: Python
Classifier: Programming Language :: Python :: 2.7
Classifier: Programming Language :: Python :: 3
Classifier: Programming Language :: Python :: 3.5
Classifier: Programming Language :: Python :: 3.6
Classifier: Programming Language :: Python :: 3.7
Classifier: Programming Language :: Python :: 3.8
Classifier: Programming Language :: Python :: 3.9
Classifier: Topic :: Internet
Classifier: Topic :: Multimedia :: Video
Classifier: Topic :: Utilities
